pyprotector/__init__.py
pyprotector/abc.py
pyprotector/constants.py
pyprotector/protector.py
pyprotector/types.py
pyprotector/modules/analysis.py
pyprotector/modules/dll.py
pyprotector/modules/dump.py
pyprotector/modules/miscellaneous.py
pyprotector/modules/process.py
pyprotector/modules/vm.py
pyprotector/utils/events.py
pyprotector/utils/exceptions.py
pyprotector/utils/http.py
pyprotector/utils/webhook.py
pyprotector/utils/windows.py
PythonProtector-1.8.dist-info/AUTHORS.md
PythonProtector-1.8.dist-info/LICENSE
PythonProtector-1.8.dist-info/METADATA
PythonProtector-1.8.dist-info/WHEEL
PythonProtector-1.8.dist-info/top_level.txt
PythonProtector-1.8.dist-info/RECORD
