Metadata-Version: 2.1
Name: PythonProtector
Version: 1.8
Summary: Library for protecting your python files
Home-page: https://github.com/xFGhoul/PythonProtecttor
Author: Ghoul & Marci
License: MIT
Project-URL: Homepage, http://ghouldev.me/PythonProtector/
Project-URL: Source, https://github.com/xFGhoul/PythonProtector
Keywords: keyauth,protection,protect,obfuscate,obfuscation,WMI,windows
Classifier: Development Status :: 3 - Alpha
Classifier: Intended Audience :: Developers
Classifier: Operating System :: Microsoft :: Windows :: Windows 10
Classifier: Operating System :: Microsoft :: Windows :: Windows 11
Classifier: Natural Language :: English
Classifier: Topic :: Internet
Classifier: Topic :: Software Development :: Libraries
Classifier: Topic :: Software Development :: Libraries :: Python Modules
Classifier: Topic :: Utilities
Classifier: License :: OSI Approved :: MIT License
Classifier: Programming Language :: Python :: 3
Classifier: Programming Language :: Python :: 3.11
Requires-Python: >=3.11
License-File: LICENSE
License-File: AUTHORS.md
Requires-Dist: humanize
Requires-Dist: loguru
Requires-Dist: discord-webhook
Requires-Dist: py-cpuinfo
Requires-Dist: command-runner
Requires-Dist: psutil
Requires-Dist: httpx
Requires-Dist: WMI
Requires-Dist: pywin32
Requires-Dist: Pillow
